rhvhauto_common_utils/__init__.py
rhvhauto_common_utils/cobbler/__init__.py
rhvhauto_common_utils/cobbler/cobbler.py
rhvhauto_common_utils/powerctl/__init__.py
rhvhauto_common_utils/powerctl/beaker.py
rhvhauto_common_utils/rhv/__init__.py
rhvhauto_common_utils/rhv/base.py
rhvhauto_common_utils-0.1.17.dist-info/WHEEL
rhvhauto_common_utils-0.1.17.dist-info/METADATA
rhvhauto_common_utils-0.1.17.dist-info/RECORD
